arbitools
tests
