Metadata-Version: 1.0
Name: arbitools
Version: 0.9792
Summary: Chess Arbiter Tools
Home-page: https://github.com/mrrookes/arbitools/archive/0.979.tar.gz
Author: David Gonzalez Gandara
Author-email: mrrookes@member.fsf.org
License: GPL
Platform: UNKNOWN
